MANIFEST.in
README.md
pip-requirements-min-django.txt
pip-requirements-test.txt
pip-requirements.txt
setup.py
database_files/__init__.py
database_files/manager.py
database_files/models.py
database_files/settings.py
database_files/storage.py
database_files/urls.py
database_files/utils.py
database_files/views.py
database_files/management/__init__.py
database_files/management/commands/__init__.py
database_files/management/commands/database_files_cleanup.py
database_files/management/commands/database_files_dump.py
database_files/management/commands/database_files_load.py
database_files/management/commands/database_files_rehash.py
database_files/migrations/0001_initial.py
database_files/migrations/__init__.py
database_files/tests/__init__.py
database_files/tests/models.py
database_files/tests/settings.py
database_files/tests/tests.py
database_files/tests/fixtures/test_files.json
database_files/tests/fixtures/test_image.png
database_files/tests/fixtures/test_image.txt
database_files/tests/media/1.txt
database_files/tests/media/1.txt.hash
django_database_files_3000.egg-info/PKG-INFO
django_database_files_3000.egg-info/SOURCES.txt
django_database_files_3000.egg-info/dependency_links.txt
django_database_files_3000.egg-info/requires.txt
django_database_files_3000.egg-info/top_level.txt