Metadata-Version: 2.1
Name: django-database-files-3000
Version: 1.0.5
Summary: A storage system for Django that stores uploaded files in both the database and file system.
Home-page: http://github.com/chrisspen/django-database-files-3000
Author: Chris Spencer
Author-email: chrisspen@gmail.com
License: UNKNOWN
Platform: UNKNOWN
Classifier: Development Status :: 6 - Mature
Classifier: Framework :: Django
Classifier: Intended Audience :: Developers
Classifier: License :: OSI Approved :: BSD License
Classifier: Operating System :: OS Independent
Classifier: Programming Language :: Python
Classifier: Programming Language :: Python :: 3.3
Classifier: Programming Language :: Python :: 3.4
Classifier: Programming Language :: Python :: 3.5
Classifier: Programming Language :: Python :: 3.6
Classifier: Programming Language :: Python :: 3.7
